keychestamp
