Metadata-Version: 2.1
Name: keychestamp
Version: 0.2.6
Summary: ACMEv2 proxy to manage clients and observe rate limits of Let's Encrypt
Home-page: https://keychest.net
Author: KeyChest Ltd
Author-email: support@keychest.net
License: UNKNOWN
Platform: UNKNOWN
Classifier: Development Status :: 3 - Alpha
Classifier: Intended Audience :: Developers
Classifier: Programming Language :: Python
Classifier: Programming Language :: Python :: 3
Classifier: Programming Language :: Python :: 3.5
Classifier: Programming Language :: Python :: 3.6
Classifier: Programming Language :: Python :: 3.7
Classifier: Topic :: Internet :: WWW/HTTP
Classifier: Topic :: Security
Classifier: Topic :: System :: Networking
Classifier: Topic :: Internet :: Proxy Servers
